neuralDX7
