Metadata-Version: 2.1
Name: neuralDX7
Version: 0.0.8
Summary: Models related to the DX7 fm synthesizer
Home-page: https://github.com/nintorac/neuralDX7
Author: Nintorac
Author-email: neuralDX7@nintorac.dev
License: MIT
Platform: UNKNOWN
Classifier: Development Status :: 3 - Alpha
Classifier: Intended Audience :: Developers
Classifier: Topic :: Software Development :: Build Tools
Classifier: License :: OSI Approved :: MIT License
Classifier: Programming Language :: Python :: 3
Classifier: Programming Language :: Python :: 3.4
Classifier: Programming Language :: Python :: 3.5
Classifier: Programming Language :: Python :: 3.6
